PyICe/LTC_plot.py
PyICe/__init__.py
PyICe/lab_core.py
PyICe/lab_gui.py
PyICe/lab_interfaces.py
PyICe/logo.py
PyICe/spi_instrument.py
PyICe/spi_interface.py
PyICe/test_lab_core.py
PyICe/tssop.ico
PyICe/tssop.png
PyICe/twi_instrument.py
PyICe/twi_interface.py
PyICe/virtual_instruments.py
PyICe/visa_wrappers.py
PyICe/bench_configuration_management/bench_configuration_management.py
PyICe/bench_configuration_management/bench_visualizer.py
PyICe/bench_configuration_management/lab_components.py
PyICe/data_utils/EMI_char_levels.py
PyICe/data_utils/LTspice_waveform_reader.py
PyICe/data_utils/__init__.py
PyICe/data_utils/create_user_files.py
PyICe/data_utils/oscilloscope_waveform_dump.py
PyICe/data_utils/pds_utils.py
PyICe/data_utils/signal_generator.py
PyICe/data_utils/spectrum_analyzer.py
PyICe/data_utils/stdf_structure_tracer.py
PyICe/data_utils/stdf_utils.py
PyICe/data_utils/touchstone_utils.py
PyICe/data_utils/units_conversions.py
PyICe/data_utils/units_parser.py
PyICe/data_utils/wave_analysis.py
PyICe/data_utils/memory_dump_analysis/Motorola_SREC_Chart.png
PyICe/data_utils/memory_dump_analysis/read_mdump.py
PyICe/data_utils/memory_dump_analysis/parse_test/golden.srec
PyICe/data_utils/memory_dump_analysis/parse_test/stowe.srec
PyICe/data_utils/memory_dump_analysis/parse_test/test_data.py
PyICe/data_utils/memory_dump_analysis/parse_test/zero_to_ff.srec
PyICe/lab_instruments/AD5259.py
PyICe/lab_instruments/AD5272.py
PyICe/lab_instruments/AD5667R.py
PyICe/lab_instruments/AD5693R.py
PyICe/lab_instruments/ADT7410.py
PyICe/lab_instruments/BR24H64.py
PyICe/lab_instruments/CAT5140.py
PyICe/lab_instruments/ENA.py
PyICe/lab_instruments/Franken_oven.py
PyICe/lab_instruments/PCF8574.py
PyICe/lab_instruments/PSA.py
PyICe/lab_instruments/TDS640A.py
PyICe/lab_instruments/TMP117.py
PyICe/lab_instruments/TestEquity_115.py
PyICe/lab_instruments/__init__.py
PyICe/lab_instruments/a3497x_instruments.py
PyICe/lab_instruments/agilent_3034a.py
PyICe/lab_instruments/agilent_33220a.py
pyice_adi-0.0.6.dist-info/METADATA
pyice_adi-0.0.6.dist-info/WHEEL
pyice_adi-0.0.6.dist-info/licenses/LICENSE
pyice_adi-0.0.6.dist-info/licenses/NOTICE
pyice_adi-0.0.6.dist-info/RECORD
