Metadata-Version: 2.3
Name: PyICe-ADI
Version: 0.0.6
Summary: A python package to aid in evaluating integrated circuits
Author-email: Dave Simmons <david.simmons@analog.com>
License-File: LICENSE
License-File: NOTICE
Classifier: Development Status :: 3 - Alpha
Classifier: Intended Audience :: Developers
Classifier: Programming Language :: Python :: 3
Classifier: Programming Language :: Python :: 3.7
Requires-Python: <=3.14,>=3.10
Requires-Dist: bokeh
Requires-Dist: cairosvg
Requires-Dist: deprecated==1.2.12
Requires-Dist: graphviz
Requires-Dist: jsonc-parser
Requires-Dist: labcomm==0.0.2
Requires-Dist: matplotlib>=3.6.0
Requires-Dist: minimalmodbus
Requires-Dist: nifgen
Requires-Dist: openpyxl
Requires-Dist: pandas
Requires-Dist: pybind11
Requires-Dist: pycairo
Requires-Dist: pyserial==3.4
Requires-Dist: pyside2
Requires-Dist: pysocks
Requires-Dist: pystdf
Requires-Dist: python-usbtmc
Requires-Dist: python-vxi11
Requires-Dist: pyusb
Requires-Dist: pyvisa
Requires-Dist: pywin32; platform_system == 'Windows'
Requires-Dist: requests==2.22.0
Requires-Dist: scikit-rf==0.26.0
Requires-Dist: scipy>=1.7
Requires-Dist: statsmodels
Requires-Dist: windows-curses==2.3.1; platform_system == 'Windows'
Requires-Dist: xlrd
Requires-Dist: xlsxwriter==1.2.9
Provides-Extra: dev
Requires-Dist: pytest; extra == 'dev'
Requires-Dist: pytest-cov; extra == 'dev'
Requires-Dist: pytest-mock; extra == 'dev'
Requires-Dist: sphinx; extra == 'dev'
Requires-Dist: sphinx-rtd-theme; extra == 'dev'
